[{"Firstname":"W3?%QM1","Midlename":"!8","Lastname":"^@181","Nickname":"2.O039&","Title":"JV\"W48TC24","Company":"37","Address":"=X8X","Telephonehome":null,"Telephonemobile":null,"Telephonework":null,"Telephonefax":null,"Email":null,"Email2":null,"Email3":null,"Homepage":null,"Birthdayday":"-","Birthdaymonth":"-","Birthdayyear":null,"Anniversaryday":"-","Anniversarymonth":"-","Anniversaryyear":null,"Group":"[none]","Secondaryaddress":null,"Secondaryhome":null,"Secondarynotes":null,"Id":null,"AllEmails":"","AllPhones":"","ContactDetailsInformation":"W3?QM1 8 ^@181\r\n2.O039\r\nJVW48TC24\r\n37\r\n=X8X"},{"Firstname":"#G9S/B","Midlename":"#T","Lastname":"","Nickname":"?9^N+\"%2B","Title":"8","Company":"5RF\"","Address":")W?C+","Telephonehome":null,"Telephonemobile":null,"Telephonework":null,"Telephonefax":null,"Email":null,"Email2":null,"Email3":null,"Homepage":null,"Birthdayday":"-","Birthdaymonth":"-","Birthdayyear":null,"Anniversaryday":"-","Anniversarymonth":"-","Anniversaryyear":null,"Group":"[none]","Secondaryaddress":null,"Secondaryhome":null,"Secondarynotes":null,"Id":null,"AllEmails":"","AllPhones":"","ContactDetailsInformation":"G9S/B T\r\n?9^N+2B\r\n8\r\n5RF\r\nW?C+"},{"Firstname":"","Midlename":"\"@Q","Lastname":"O\\,SWP","Nickname":"J$9LY-","Title":"'LB0E:E1!N","Company":"Q,W%^","Address":"\\","Telephonehome":null,"Telephonemobile":null,"Telephonework":null,"Telephonefax":null,"Email":null,"Email2":null,"Email3":null,"Homepage":null,"Birthdayday":"-","Birthdaymonth":"-","Birthdayyear":null,"Anniversaryday":"-","Anniversarymonth":"-","Anniversaryyear":null,"Group":"[none]","Secondaryaddress":null,"Secondaryhome":null,"Secondarynotes":null,"Id":null,"AllEmails":"","AllPhones":"","ContactDetailsInformation":"@Q O\\,SWP\r\nJ9LY-\r\nLB0E:E1N\r\nQ,W^\r\n\\"},{"Firstname":"+9.EBOE<","Midlename":"-'U_W$","Lastname":"C+_!F","Nickname":"$W]E+7KE;","Title":"K#MP","Company":";U(.0:Q9","Address":"&+3B","Telephonehome":null,"Telephonemobile":null,"Telephonework":null,"Telephonefax":null,"Email":null,"Email2":null,"Email3":null,"Homepage":null,"Birthdayday":"-","Birthdaymonth":"-","Birthdayyear":null,"Anniversaryday":"-","Anniversarymonth":"-","Anniversaryyear":null,"Group":"[none]","Secondaryaddress":null,"Secondaryhome":null,"Secondarynotes":null,"Id":null,"AllEmails":"","AllPhones":"","ContactDetailsInformation":"+9.EBOE< -U_W C+_F\r\nW]E+7KE;\r\nKMP\r\n;U.0:Q9\r\n+3B"},{"Firstname":"CA\\4SV","Midlename":"CC5D/2NH","Lastname":"Z;)","Nickname":"77","Title":"GYM7FB","Company":"[NN","Address":"J#>B@OA","Telephonehome":null,"Telephonemobile":null,"Telephonework":null,"Telephonefax":null,"Email":null,"Email2":null,"Email3":null,"Homepage":null,"Birthdayday":"-","Birthdaymonth":"-","Birthdayyear":null,"Anniversaryday":"-","Anniversarymonth":"-","Anniversaryyear":null,"Group":"[none]","Secondaryaddress":null,"Secondaryhome":null,"Secondarynotes":null,"Id":null,"AllEmails":"","AllPhones":"","ContactDetailsInformation":"CA\\4SV CC5D/2NH Z;\r\n77\r\nGYM7FB\r\n[NN\r\nJ>B@OA"}]